jogospybr/__init__.py
jogospybr/advinhacao.py
jogospybr/jogodedados.py
jogospybr/jokenpo.py
jogospybr/megasena.py
jogospybr/parouimpar.py
jogospybr-0.0.2.dist-info/METADATA
jogospybr-0.0.2.dist-info/WHEEL
jogospybr-0.0.2.dist-info/top_level.txt
jogospybr-0.0.2.dist-info/RECORD
