Metadata-Version: 2.1
Name: jogospybr
Version: 0.0.2
Summary: Some games from Brazil in Python
Home-page: https://github.com/felipebbarreto/DIOgames.git
Author: felipeb_barreto
Author-email: felipebbarreto22@gmail.com
License: UNKNOWN
Platform: UNKNOWN
Requires-Python: >=3.3
